inflection_fishbowl-0.2.0.dist-info/METADATA
inflection_fishbowl-0.2.0.dist-info/WHEEL
fishbowl/__init__.py
fishbowl/fishbowl.pypy39-pp73-x86-linux-gnu.so
inflection_fishbowl-0.2.0.dist-info/RECORD
