Metadata-Version: 2.1
Name: inflection-fishbowl
Version: 0.2.0
Classifier: Programming Language :: Rust
Classifier: Programming Language :: Python :: Implementation :: CPython
Requires-Python: >=3.9
